2-bit comprator/2-comp.v
module two_bit_comparator (
  input [1:0] a, b
  output reg eq, lt, gt
);

  always @(a, b) begin
    eq <= (a == b);
    lt <= (a < b);
    gt <= (a > b);
  end

endmodule

2-bit comprator/2com_tb.v
module two_bit_comparator_tb;

  reg [1:0] a, b;
  wire eq, lt, gt;

  two_bit_comparator uut (
    .a(a),
    .b(b),
    .eq(eq),
    .lt(lt),
    .gt(gt)
  );

  initial begin
  $monitor($time,"a=%b,b=%b,eq=%b,lt=%b,gt=%b",a,b,eq,lt,gt);
    $dumpfile("two_bit_comparator.vcd");
    $dumpvars(0, two_bit_comparator_tb);

    a = 2'b00;
    b = 2'b00;
    #10;
    a = 2'b01;
    b = 2'b00;
    #10;
    a = 2'b10;
    b = 2'b00;
    #10;
    a = 2'b11;
    b = 2'b00;
    #10;
    a = 2'b00;
    b = 2'b01;
    #10;
    a = 2'b01;
    b = 2'b01;
    #10;
    a = 2'b10;
    b = 2'b01;
    #10;
    a = 2'b11;
    b = 2'b01;
    #10;
    a = 2'b00;
    b = 2'b10;
    #10;
    a = 2'b01;
    b = 2'b10;
    #10;
    a = 2'b10;
    b = 2'b10;
    #10;
    a = 2'b11;
    b = 2'b10;
    #10;
    a = 2'b00;
    b = 2'b11;
    #10;
    a = 2'b01;
    b = 2'b11;
    #10;
    a = 2'b10;
    b = 2'b11;
    #10;
    a = 2'b11;
    b = 2'b11;
    #10;

    $finish;
  end

endmodule

2-bit comprator/two_bit_comparator.vcd
$date
	Thu Oct 19 12:33:59 2023
$end
$version
	ModelSim Version 10.5b
$end
$timescale
	1ps
$end

$scope module two_bit_comparator_tb $end
$var reg 2 ! a [1:0] $end
$var reg 2 " b [1:0] $end
$var wire 1 # eq $end
$var wire 1 $ lt $end
$var wire 1 % gt $end

$scope module uut $end
$var wire 1 & a [1] $end
$var wire 1 ' a [0] $end
$var wire 1 ( b [1] $end
$var wire 1 ) b [0] $end
$var reg 1 * eq $end
$var reg 1 + lt $end
$var reg 1 , gt $end
$upscope $end
$upscope $end
$enddefinitions $end
#0
$dumpvars
b0 !
b0 "
1*
0+
0,
1#
0$
0%
0)
0(
0'
0&
$end
#10
b1 !
1'
0*
1,
0#
1%
#20
b10 !
0'
1&
#30
b11 !
1'
#40
b0 !
b1 "
1)
0'
0&
1+
0,
1$
0%
#50
b1 !
1'
1*
0+
1#
0$
#60
b10 !
0'
1&
0*
1,
0#
1%
#70
b11 !
1'
#80
b0 !
b10 "
0)
1(
0'
0&
1+
0,
1$
0%
#90
b1 !
1'
#100
b10 !
0'
1&
1*
0+
1#
0$
